{
  "Object": {
    "GUID": "ae1d63",
    "Name": "Bag",
    "Transform": {
      "posX": 66.82925,
      "posY": 2.036101,
      "posZ": -15.7883816,
      "rotX": -7.43447459e-13,
      "rotY": 179.999634,
      "rotZ": -2.35121263e-7,
      "scaleX": 1,
      "scaleY": 1,
      "scaleZ": 1
    },
    "Nickname": "Mystery Bag",
    "Description": "",
    "GMNotes": "",
    "ColorDiffuse": {
      "r": 0.905882359,
      "g": 0.921568632,
      "b": 0
    },
    "LayoutGroupSortIndex": 0,
    "Value": 0,
    "Locked": false,
    "Grid": true,
    "Snap": true,
    "IgnoreFoW": false,
    "MeasureMovement": false,
    "DragSelectable": true,
    "Autoraise": true,
    "Sticky": true,
    "Tooltip": true,
    "GridProjection": false,
    "HideWhenFaceDown": false,
    "Hands": false,
    "MaterialIndex": -1,
    "MeshIndex": -1,
    "Bag": {
      "Order": 0
    },
    "LuaScript": "#include ./Mystery_Bag.ae1d63.lua",
    "LuaScriptState": "#include ./Mystery_Bag.ae1d63.state.json",
    "XmlUI": "",
    "ContainedObjects": []
  },
  "StatesPaths": {},
  "ContainedObjectPaths": [
    "Deck.f6028f.json"
  ]
}
