{
  "Object": {
    "GUID": "826bcc",
    "Name": "CardCustom",
    "Transform": {
      "posX": 109.422478,
      "posY": 4.683049,
      "posZ": 32.7087173,
      "rotX": 1.16119892e-7,
      "rotY": 89.9999847,
      "rotZ": -8.900681e-8,
      "scaleX": 2.92840672,
      "scaleY": 1,
      "scaleZ": 2.92840672
    },
    "Nickname": "The Island of Dr. Zola",
    "Description": "",
    "GMNotes": "",
    "ColorDiffuse": {
      "r": 0.713235259,
      "g": 0.713235259,
      "b": 0.713235259
    },
    "LayoutGroupSortIndex": 0,
    "Value": 0,
    "Locked": false,
    "Grid": true,
    "Snap": true,
    "IgnoreFoW": false,
    "MeasureMovement": false,
    "DragSelectable": true,
    "Autoraise": true,
    "Sticky": true,
    "Tooltip": true,
    "GridProjection": false,
    "HideWhenFaceDown": false,
    "Hands": true,
    "CardID": 796400,
    "SidewaysCard": true,
    "CustomDeck": {
      "7964": {
        "FaceURL": "http://cloud-3.steamusercontent.com/ugc/1618437358526293802/D3DEE62F07288AE3DA6FE3FEB31C2730701D96B7/",
        "BackURL": "http://cloud-3.steamusercontent.com/ugc/1618437358526294005/0F4DF537FA98376EAF27CB5A44E3EF70BE2AC955/",
        "NumWidth": 1,
        "NumHeight": 1,
        "BackIsHidden": true,
        "UniqueBack": false,
        "Type": 0
      }
    },
    "LuaScript": "",
    "LuaScriptState": "",
    "XmlUI": ""
  },
  "StatesPaths": {}
}

}
