{
  "Object": {
    "GUID": "7191d4",
    "Name": "Card",
    "Transform": {
      "posX": 13.7499809,
      "posY": 0.9712169,
      "posZ": 10.2500305,
      "rotX": 0.02351513,
      "rotY": 179.999954,
      "rotZ": 359.8363,
      "scaleX": 1,
      "scaleY": 1,
      "scaleZ": 1
    },
    "Nickname": "Overburdened",
    "Description": "",
    "GMNotes": "",
    "AltLookAngle": {
      "x": 0,
      "y": 0,
      "z": 0
    },
    "ColorDiffuse": {
      "r": 1,
      "g": 1,
      "b": 1
    },
    "LayoutGroupSortIndex": 0,
    "Value": 0,
    "Locked": false,
    "Grid": true,
    "Snap": true,
    "IgnoreFoW": false,
    "MeasureMovement": false,
    "DragSelectable": true,
    "Autoraise": true,
    "Sticky": true,
    "Tooltip": true,
    "GridProjection": false,
    "HideWhenFaceDown": true,
    "Hands": true,
    "CardID": 44200,
    "SidewaysCard": false,
    "CustomDeck": {
      "442": {
        "FaceURL": "https://dcqvlrey92bew.cloudfront.net/40203.jpg",
        "BackURL": "https://steamusercontent-a.akamaihd.net/ugc/1795242553066035592/AEE6A404260E9B5DEE79D2B19CB39F982DCA574D/",
        "NumWidth": 1,
        "NumHeight": 1,
        "BackIsHidden": false,
        "UniqueBack": false,
        "Type": 0
      }
    },
    "LuaScript": "",
    "LuaScriptState": "",
    "XmlUI": ""
  },
  "StatesPaths": {}
}
