{
  "Object": {
    "GUID": "d94290",
    "Name": "Deck",
    "Transform": {
      "posX": 102.202011,
      "posY": 6.43592834,
      "posZ": 39.0411873,
      "rotX": 2.59574421e-7,
      "rotY": 180.021927,
      "rotZ": 180,
      "scaleX": 1.27,
      "scaleY": 1,
      "scaleZ": 1.27
    },
    "Nickname": "Hulk",
    "Description": "",
    "GMNotes": "",
    "ColorDiffuse": {
      "r": 0.713235259,
      "g": 0.713235259,
      "b": 0.713235259
    },
    "LayoutGroupSortIndex": 0,
    "Value": 0,
    "Locked": false,
    "Grid": true,
    "Snap": true,
    "IgnoreFoW": false,
    "MeasureMovement": false,
    "DragSelectable": true,
    "Autoraise": true,
    "Sticky": true,
    "Tooltip": true,
    "GridProjection": false,
    "HideWhenFaceDown": true,
    "Hands": false,
    "SidewaysCard": false,
    "DeckIDs": [
      732100,
      732100,
      732100,
      733817,
      733818,
      733819,
      733821,
      465210,
      465308,
      465308,
      733900,
      733900,
      733900,
      597000,
      597000,
      597000,
      596400,
      596400,
      596400,
      734100,
      734200,
      732000,
      734000,
      734000,
      734000,
      596100,
      731400,
      731500,
      731600,
      731600,
      597200,
      597200,
      596900,
      596900,
      596800,
      596800,
      596000,
      596000,
      734300,
      734300
    ],
    "CustomDeck": {
      "4652": {
        "FaceURL": "http://cloud-3.steamusercontent.com/ugc/782995698740286845/94BB2B7D9097163C8476202707FDC57BFCEF456C/",
        "BackURL": "http://cloud-3.steamusercontent.com/ugc/767229025789764879/AEE6A404260E9B5DEE79D2B19CB39F982DCA574D/",
        "NumWidth": 5,
        "NumHeight": 5,
        "BackIsHidden": false,
        "UniqueBack": false,
        "Type": 0
      },
      "4653": {
        "FaceURL": "http://cloud-3.steamusercontent.com/ugc/767229025789775463/9047F42DB200C97441FCBE547A01FDFCBB104784/",
        "BackURL": "http://cloud-3.steamusercontent.com/ugc/767229025789764879/AEE6A404260E9B5DEE79D2B19CB39F982DCA574D/",
        "NumWidth": 5,
        "NumHeight": 5,
        "BackIsHidden": false,
        "UniqueBack": false,
        "Type": 0
      },
      "5960": {
        "FaceURL": "http://cloud-3.steamusercontent.com/ugc/1246883024980476048/CF695DB52E0A0A8CDFEB58B3A114DCBE71B62201/",
        "BackURL": "http://cloud-3.steamusercontent.com/ugc/770610821574915156/AEE6A404260E9B5DEE79D2B19CB39F982DCA574D/",
        "NumWidth": 1,
        "NumHeight": 1,
        "BackIsHidden": true,
        "UniqueBack": false,
        "Type": 0
      },
      "5961": {
        "FaceURL": "http://cloud-3.steamusercontent.com/ugc/1246883024980476933/D029FCAA559AE876C427650F59FF6799CA0F1FAE/",
        "BackURL": "http://cloud-3.steamusercontent.com/ugc/770610821574915156/AEE6A404260E9B5DEE79D2B19CB39F982DCA574D/",
        "NumWidth": 1,
        "NumHeight": 1,
        "BackIsHidden": true,
        "UniqueBack": false,
        "Type": 0
      },
      "5964": {
        "FaceURL": "http://cloud-3.steamusercontent.com/ugc/1246883024980479606/33F5E5112164B5E94C2FCCA2D388096C941C0F8B/",
        "BackURL": "http://cloud-3.steamusercontent.com/ugc/770610821574915156/AEE6A404260E9B5DEE79D2B19CB39F982DCA574D/",
        "NumWidth": 1,
        "NumHeight": 1,
        "BackIsHidden": true,
        "UniqueBack": false,
        "Type": 0
      },
      "5968": {
        "FaceURL": "http://cloud-3.steamusercontent.com/ugc/1246883024980484635/C4158D4C4B2BA2A8AEAC4F6B4245953B02AD1348/",
        "BackURL": "http://cloud-3.steamusercontent.com/ugc/770610821574915156/AEE6A404260E9B5DEE79D2B19CB39F982DCA574D/",
        "NumWidth": 1,
        "NumHeight": 1,
        "BackIsHidden": true,
        "UniqueBack": false,
        "Type": 0
      },
      "5969": {
        "FaceURL": "http://cloud-3.steamusercontent.com/ugc/1246883024980485340/BC9AEB80F4992BCB673255EE49565B8495E84FA9/",
        "BackURL": "http://cloud-3.steamusercontent.com/ugc/770610821574915156/AEE6A404260E9B5DEE79D2B19CB39F982DCA574D/",
        "NumWidth": 1,
        "NumHeight": 1,
        "BackIsHidden": true,
        "UniqueBack": false,
        "Type": 0
      },
      "5970": {
        "FaceURL": "http://cloud-3.steamusercontent.com/ugc/1246883024980486002/E4CCF0F88D0DA6AA2EB153607CE6FDF402373A4B/",
        "BackURL": "http://cloud-3.steamusercontent.com/ugc/770610821574915156/AEE6A404260E9B5DEE79D2B19CB39F982DCA574D/",
        "NumWidth": 1,
        "NumHeight": 1,
        "BackIsHidden": true,
        "UniqueBack": false,
        "Type": 0
      },
      "5972": {
        "FaceURL": "http://cloud-3.steamusercontent.com/ugc/1246883024980487557/03DC6B22592348F09968CDCE0726AC3A2A67B234/",
        "BackURL": "http://cloud-3.steamusercontent.com/ugc/770610821574915156/AEE6A404260E9B5DEE79D2B19CB39F982DCA574D/",
        "NumWidth": 1,
        "NumHeight": 1,
        "BackIsHidden": true,
        "UniqueBack": false,
        "Type": 0
      },
      "7314": {
        "FaceURL": "http://cloud-3.steamusercontent.com/ugc/1246883024980471361/50A7CC1453C6C6E9FC363E1827B99221C022BCB3/",
        "BackURL": "http://cloud-3.steamusercontent.com/ugc/770610821574915156/AEE6A404260E9B5DEE79D2B19CB39F982DCA574D/",
        "NumWidth": 1,
        "NumHeight": 1,
        "BackIsHidden": true,
        "UniqueBack": false,
        "Type": 0
      },
      "7315": {
        "FaceURL": "http://cloud-3.steamusercontent.com/ugc/1246883024980469962/460D0F0F89755A7516E8689491F404DE95AF419A/",
        "BackURL": "http://cloud-3.steamusercontent.com/ugc/770610821574915156/AEE6A404260E9B5DEE79D2B19CB39F982DCA574D/",
        "NumWidth": 1,
        "NumHeight": 1,
        "BackIsHidden": true,
        "UniqueBack": false,
        "Type": 0
      },
      "7316": {
        "FaceURL": "http://cloud-3.steamusercontent.com/ugc/1246883024980478690/876A05FBFA6C26E4FAFF781CB27EE14B5AD46804/",
        "BackURL": "http://cloud-3.steamusercontent.com/ugc/770610821574915156/AEE6A404260E9B5DEE79D2B19CB39F982DCA574D/",
        "NumWidth": 1,
        "NumHeight": 1,
        "BackIsHidden": true,
        "UniqueBack": false,
        "Type": 0
      },
      "7320": {
        "FaceURL": "http://cloud-3.steamusercontent.com/ugc/1246883024980483794/02C763704FAADF7FE964480187EC001B6C9BB6F4/",
        "BackURL": "http://cloud-3.steamusercontent.com/ugc/770610821574915156/AEE6A404260E9B5DEE79D2B19CB39F982DCA574D/",
        "NumWidth": 1,
        "NumHeight": 1,
        "BackIsHidden": true,
        "UniqueBack": false,
        "Type": 0
      },
      "7321": {
        "FaceURL": "http://cloud-3.steamusercontent.com/ugc/1246883024980486730/405B5B8AAFF3A9D25C523C45B097926D013E51A7/",
        "BackURL": "http://cloud-3.steamusercontent.com/ugc/770610821574915156/AEE6A404260E9B5DEE79D2B19CB39F982DCA574D/",
        "NumWidth": 1,
        "NumHeight": 1,
        "BackIsHidden": true,
        "UniqueBack": false,
        "Type": 0
      },
      "7338": {
        "FaceURL": "http://cloud-3.steamusercontent.com/ugc/767229025789778613/5B577B95A5871E9B86AB945A2FF8BA0BE4E8A6CA/",
        "BackURL": "http://cloud-3.steamusercontent.com/ugc/767229025789764879/AEE6A404260E9B5DEE79D2B19CB39F982DCA574D/",
        "NumWidth": 5,
        "NumHeight": 5,
        "BackIsHidden": false,
        "UniqueBack": false,
        "Type": 0
      },
      "7339": {
        "FaceURL": "http://cloud-3.steamusercontent.com/ugc/1246883024980490322/B7F2B51F9EDCF21FE0FF0ACEB2DFEFB69BE46656/",
        "BackURL": "http://cloud-3.steamusercontent.com/ugc/770610821574915156/AEE6A404260E9B5DEE79D2B19CB39F982DCA574D/",
        "NumWidth": 1,
        "NumHeight": 1,
        "BackIsHidden": true,
        "UniqueBack": false,
        "Type": 0
      },
      "7340": {
        "FaceURL": "http://cloud-3.steamusercontent.com/ugc/1246883024980473475/22009E43E8EE270170D46F89170BAFE40E17F330/",
        "BackURL": "http://cloud-3.steamusercontent.com/ugc/770610821574915156/AEE6A404260E9B5DEE79D2B19CB39F982DCA574D/",
        "NumWidth": 1,
        "NumHeight": 1,
        "BackIsHidden": true,
        "UniqueBack": false,
        "Type": 0
      },
      "7341": {
        "FaceURL": "http://cloud-3.steamusercontent.com/ugc/1246883024980472103/C4C403F49983268400C69D2F07F8B3E50CCD0B87/",
        "BackURL": "http://cloud-3.steamusercontent.com/ugc/770610821574915156/AEE6A404260E9B5DEE79D2B19CB39F982DCA574D/",
        "NumWidth": 1,
        "NumHeight": 1,
        "BackIsHidden": true,
        "UniqueBack": false,
        "Type": 0
      },
      "7342": {
        "FaceURL": "http://cloud-3.steamusercontent.com/ugc/1246883024980483092/0F87950815B20ED92B75300CF982CE0215536099/",
        "BackURL": "http://cloud-3.steamusercontent.com/ugc/770610821574915156/AEE6A404260E9B5DEE79D2B19CB39F982DCA574D/",
        "NumWidth": 1,
        "NumHeight": 1,
        "BackIsHidden": true,
        "UniqueBack": false,
        "Type": 0
      },
      "7343": {
        "FaceURL": "http://cloud-3.steamusercontent.com/ugc/1246883024980472728/4E6448BCA19035A4B02A2A1B7D773BC82253B564/",
        "BackURL": "http://cloud-3.steamusercontent.com/ugc/770610821574915156/AEE6A404260E9B5DEE79D2B19CB39F982DCA574D/",
        "NumWidth": 1,
        "NumHeight": 1,
        "BackIsHidden": true,
        "UniqueBack": false,
        "Type": 0
      }
    },
    "LuaScript": "",
    "LuaScriptState": "",
    "XmlUI": "",
    "ContainedObjects": []
  },
  "StatesPaths": {},
  "ContainedObjectPaths": [
    "To_the_Rescue!.adc402.732100.json",
    "To_the_Rescue!.97414d.732100.json",
    "To_the_Rescue!.22306f.732100.json",
    "Energy.54e7fc.733817.json",
    "Genius.689dea.733818.json",
    "Strength.6656d7.733819.json",
    "Helicarrier.167485.733821.json",
    "Avengers_Mansion.600a09.465210.json",
    "The_Power_of_Aggression.9893cd.465308.json",
    "The_Power_of_Aggression.aa836e.465308.json",
    "You_ll_Pay_for_That!.1fc538.733900.json",
    "You_ll_Pay_for_That!.83e294.733900.json",
    "You_ll_Pay_for_That!.3f4f69.733900.json",
    "Toe_to_Toe.13547b.597000.json",
    "Toe_to_Toe.32be65.597000.json",
    "Toe_to_Toe.13547b.597000.json",
    "Martial_Prowess.a5838b.596400.json",
    "Martial_Prowess.864d9e.596400.json",
    "Martial_Prowess.a5838b.596400.json",
    "Brawn.07a974.734100.json",
    "Sentry.18b73f.734200.json",
    "She-Hulk.3705c5.732000.json",
    "Drop_Kick.492455.734000.json",
    "Drop_Kick.f95374.734000.json",
    "Drop_Kick.492455.734000.json",
    "Immovable_Object.66c8e2.596100.json",
    "Boundless_Rage.5390d6.731400.json",
    "Banner_s_Laboratory.b37f38.731500.json",
    "Limitless_Strength.f33e75.731600.json",
    "Limitless_Strength.6943ce.731600.json",
    "Unstoppable_Force.bc9d67.597200.json",
    "Unstoppable_Force.3478e7.597200.json",
    "Thunderclap.5033c4.596900.json",
    "Thunderclap.362549.596900.json",
    "Sub-Orbital_Leap.46e5f4.596800.json",
    "Sub-Orbital_Leap.adfee3.596800.json",
    "Hulk_Smash.ca3614.596000.json",
    "Hulk_Smash.44e21f.596000.json",
    "Crushing_Blow.ea870b.734300.json",
    "Crushing_Blow.0b4a08.734300.json"
  ]
}
