{
  "Object": {
    "GUID": "3a2dc7",
    "Name": "Deck",
    "Transform": {
      "posX": -35.25,
      "posY": 1.500611,
      "posZ": 0.25,
      "rotX": 0.00298259035,
      "rotY": 180.012589,
      "rotZ": 7.157104e-7,
      "scaleX": 1.27,
      "scaleY": 1,
      "scaleZ": 1.27
    },
    "Nickname": "System Shock",
    "Description": "",
    "GMNotes": "",
    "AltLookAngle": {
      "x": 0,
      "y": 0,
      "z": 0
    },
    "ColorDiffuse": {
      "r": 0.713235259,
      "g": 0.713235259,
      "b": 0.713235259
    },
    "LayoutGroupSortIndex": 0,
    "Value": 0,
    "Locked": false,
    "Grid": true,
    "Snap": true,
    "IgnoreFoW": false,
    "MeasureMovement": false,
    "DragSelectable": true,
    "Autoraise": true,
    "Sticky": true,
    "Tooltip": true,
    "GridProjection": false,
    "HideWhenFaceDown": true,
    "Hands": false,
    "SidewaysCard": false,
    "DeckIDs": [
      4807,
      4807,
      4807,
      4807
    ],
    "CustomDeck": {
      "48": {
        "FaceURL": "http://cloud-3.steamusercontent.com/ugc/1711917883467537825/05F15B9509CD06496BDFB5EED67004B7B4AEE4B4/",
        "BackURL": "http://cloud-3.steamusercontent.com/ugc/1264897305960075747/AEE6A404260E9B5DEE79D2B19CB39F982DCA574D/",
        "NumWidth": 4,
        "NumHeight": 3,
        "BackIsHidden": false,
        "UniqueBack": false,
        "Type": 0
      }
    },
    "LuaScript": "",
    "LuaScriptState": "",
    "XmlUI": "",
    "ContainedObjects": []
  },
  "StatesPaths": {},
  "ContainedObjectPaths": [
    "System_Shock.65d141.4807.json",
    "System_Shock.91cc05.4807.json",
    "System_Shock.3723b3.4807.json",
    "System_Shock.073ecf.4807.json"
  ]
}
