{
  "Object": {
    "GUID": "90d2ae",
    "Name": "Deck",
    "Transform": {
      "posX": 36.00002,
      "posY": 3.56862473,
      "posZ": 22.00002,
      "rotX": 0.07586194,
      "rotY": 89.99403,
      "rotZ": 0.0162784941,
      "scaleX": 1.93762064,
      "scaleY": 1,
      "scaleZ": 1.93762064
    },
    "Nickname": "Kang Main Scheme",
    "Description": "Scanned and imported by Unicorn",
    "GMNotes": "",
    "ColorDiffuse": {
      "r": 0.713235259,
      "g": 0.713235259,
      "b": 0.713235259
    },
    "LayoutGroupSortIndex": 0,
    "Value": 0,
    "Locked": false,
    "Grid": true,
    "Snap": true,
    "IgnoreFoW": false,
    "MeasureMovement": false,
    "DragSelectable": true,
    "Autoraise": true,
    "Sticky": true,
    "Tooltip": true,
    "GridProjection": false,
    "HideWhenFaceDown": true,
    "Hands": false,
    "SidewaysCard": true,
    "DeckIDs": [
      1100,
      1000,
      900,
      800,
      700,
      600,
      500
    ],
    "CustomDeck": {
      "5": {
        "FaceURL": "http://cloud-3.steamusercontent.com/ugc/1833527325297268919/38821504D48E122EFD0A03FFE6CFD8AABDEB8050/",
        "BackURL": "http://cloud-3.steamusercontent.com/ugc/1833527325297269103/F8DAEA671123A8638498C376F027550956308468/",
        "NumWidth": 1,
        "NumHeight": 1,
        "BackIsHidden": true,
        "UniqueBack": false,
        "Type": 0
      },
      "6": {
        "FaceURL": "http://cloud-3.steamusercontent.com/ugc/1833527325297269453/505B8875C7158ACC223FE88FFE8622F59A61AF27/",
        "BackURL": "http://cloud-3.steamusercontent.com/ugc/1833527325297269617/1B369CE9072A33172853CA4439152FB8B666D00D/",
        "NumWidth": 1,
        "NumHeight": 1,
        "BackIsHidden": true,
        "UniqueBack": false,
        "Type": 0
      },
      "7": {
        "FaceURL": "http://cloud-3.steamusercontent.com/ugc/1833527325297270033/590C27A6F8D435F26B2E78DC0FE95216BA038B2E/",
        "BackURL": "http://cloud-3.steamusercontent.com/ugc/1833527325297270237/E8FBA11E3AEE44215027E87C87DAC09999E33666/",
        "NumWidth": 1,
        "NumHeight": 1,
        "BackIsHidden": true,
        "UniqueBack": false,
        "Type": 0
      },
      "8": {
        "FaceURL": "http://cloud-3.steamusercontent.com/ugc/1833527325297270610/C583EDD0609FE6E7EDB392B14F8D9E56BFBAE1CD/",
        "BackURL": "http://cloud-3.steamusercontent.com/ugc/1833527325297270789/C337BE40FB2127D5C2B6BA3A956103CC736A47DE/",
        "NumWidth": 1,
        "NumHeight": 1,
        "BackIsHidden": true,
        "UniqueBack": false,
        "Type": 0
      },
      "9": {
        "FaceURL": "http://cloud-3.steamusercontent.com/ugc/1833527325297271182/5FAEF9A2A2BDAB9D7A9FDD1899FCB4D5B28D03B9/",
        "BackURL": "http://cloud-3.steamusercontent.com/ugc/1833527325297271381/E1FA44877CAC91A929DE5F3F7ABFCCBC1B8208CB/",
        "NumWidth": 1,
        "NumHeight": 1,
        "BackIsHidden": true,
        "UniqueBack": false,
        "Type": 0
      },
      "10": {
        "FaceURL": "http://cloud-3.steamusercontent.com/ugc/1833527325297271778/16EEC73DABAAA0770A6353AAF6286304AA1C951B/",
        "BackURL": "http://cloud-3.steamusercontent.com/ugc/1833527325297272002/4026E8A51EAF664340B3646AEAA6CCBB57EFECA2/",
        "NumWidth": 1,
        "NumHeight": 1,
        "BackIsHidden": true,
        "UniqueBack": false,
        "Type": 0
      },
      "11": {
        "FaceURL": "http://cloud-3.steamusercontent.com/ugc/1833527325297272485/55966A4761A5B1AEA863AEED0902024ACA81C7A6/",
        "BackURL": "http://cloud-3.steamusercontent.com/ugc/1833527325297272854/740B6863DACA137901E0872C64F6AE631E94C82B/",
        "NumWidth": 1,
        "NumHeight": 1,
        "BackIsHidden": true,
        "UniqueBack": false,
        "Type": 0
      }
    },
    "LuaScript": "",
    "LuaScriptState": "",
    "XmlUI": "",
    "ContainedObjects": []
  },
  "StatesPaths": {},
  "ContainedObjectPaths": [
    "Kang_s_Wrath.df1d64.1100.json",
    "The_Present_Future_War.63f963.1000.json",
    "The_Realm_of_Rama-Tut.ecc23c.900.json",
    "Inexorable_Fate.a01d9e.800.json",
    "The_Chronopolis.45920f.700.json",
    "The_Master_of_Time.1989b3.600.json",
    "Kang_s_Arrival.0babce.500.json"
  ]
}
