{
  "Object": {
    "GUID": "fcd3b5",
    "Name": "Deck",
    "Transform": {
      "posX": 102.542046,
      "posY": 38.75038,
      "posZ": -23.21632,
      "rotX": -3.74262754e-8,
      "rotY": 180,
      "rotZ": 180,
      "scaleX": 1.88,
      "scaleY": 1,
      "scaleZ": 1.88
    },
    "Nickname": "Mystique Modular Set",
    "Description": "Scanned and imported by Unicorn",
    "GMNotes": "",
    "AltLookAngle": {
      "x": 0,
      "y": 0,
      "z": 0
    },
    "ColorDiffuse": {
      "r": 0.713235259,
      "g": 0.713235259,
      "b": 0.713235259
    },
    "LayoutGroupSortIndex": 0,
    "Value": 0,
    "Locked": false,
    "Grid": true,
    "Snap": true,
    "IgnoreFoW": false,
    "MeasureMovement": false,
    "DragSelectable": true,
    "Autoraise": true,
    "Sticky": true,
    "Tooltip": true,
    "GridProjection": false,
    "HideWhenFaceDown": true,
    "Hands": false,
    "SidewaysCard": false,
    "DeckIDs": [
      974603,
      974602,
      974601,
      704,
      974600
    ],
    "CustomDeck": {
      "7": {
        "FaceURL": "http://cloud-3.steamusercontent.com/ugc/1829048392450933486/0BF76DA0C35CCAD0DDF18325847BA8FA244F5C27/",
        "BackURL": "http://cloud-3.steamusercontent.com/ugc/1829048392450924385/59B873A9956467496A0CF001A70570635C315BEB/",
        "NumWidth": 4,
        "NumHeight": 2,
        "BackIsHidden": false,
        "UniqueBack": false,
        "Type": 0
      },
      "9746": {
        "FaceURL": "http://cloud-3.steamusercontent.com/ugc/1829048392450931352/7DC64A07FE73AF245D24BBA8CCBA4E5AE71D2CFF/",
        "BackURL": "http://cloud-3.steamusercontent.com/ugc/1829048392450924385/59B873A9956467496A0CF001A70570635C315BEB/",
        "NumWidth": 3,
        "NumHeight": 2,
        "BackIsHidden": false,
        "UniqueBack": false,
        "Type": 0
      }
    },
    "LuaScript": "",
    "LuaScriptState": "",
    "XmlUI": "",
    "ContainedObjects": []
  },
  "StatesPaths": {},
  "ContainedObjectPaths": [
    "Shapeshifter_Surprise.68e304.974603.json",
    "Infiltration.56c219.974602.json",
    "Infiltration.142fdd.974601.json",
    "Metamorphic_Mayhem.bfe5ca.704.json",
    "Mystique.25a8f1.974600.json"
  ]
}
