{"ml":{"00f91e":{"lock":true,"pos":{"x":-41.205,"y":0.9644,"z":-17.085},"rot":{"x":0,"y":180,"z":0.0187}},"08b295":{"lock":true,"pos":{"x":-51.634,"y":1.0678,"z":-11.5694},"rot":{"x":0,"y":179.9999,"z":0.0187}},"45b260":{"lock":false,"pos":{"x":-21.105,"y":1.0062,"z":35.175},"rot":{"x":0,"y":180,"z":0}},"6a4c70":{"lock":false,"pos":{"x":-49.6242,"y":1.2806,"z":-21.7287},"rot":{"x":0,"y":180.0008,"z":180.0187}},"c9abd6":{"lock":false,"pos":{"x":-51.1335,"y":1.0812,"z":-16.0693},"rot":{"x":0,"y":180,"z":180.0187}},"d7503a":{"lock":false,"pos":{"x":-12.75,"y":0.9736,"z":22.25},"rot":{"x":0,"y":179.9743,"z":180}}},"ml2":{"00f91e":{"lock":true,"pos":{"x":-41.205,"y":0.9644,"z":-17.085},"rot":{"x":0,"y":180,"z":0.0187}},"08b295":{"lock":true,"pos":{"x":-51.634,"y":1.0678,"z":-11.5694},"rot":{"x":0,"y":179.9999,"z":0.0187}},"45b260":{"lock":false,"pos":{"x":-21.105,"y":1.0062,"z":35.175},"rot":{"x":0,"y":180,"z":0}},"65e798":{"lock":false,"pos":{"x":-49.6243,"y":1.1603,"z":-21.7287},"rot":{"x":0,"y":179.9662,"z":0.0187}},"c9abd6":{"lock":false,"pos":{"x":-51.1335,"y":1.0812,"z":-16.0693},"rot":{"x":0,"y":180,"z":180.0187}},"d7503a":{"lock":false,"pos":{"x":-12.75,"y":0.9736,"z":22.25},"rot":{"x":0,"y":179.9743,"z":180}}},"ml3":{"00f91e":{"lock":true,"pos":{"x":-13.7113,"y":0.96,"z":-17.7527},"rot":{"x":0,"y":179.9851,"z":0}},"08b295":{"lock":true,"pos":{"x":-24.1417,"y":1.06,"z":-12.2398},"rot":{"x":0,"y":179.9845,"z":0}},"45b260":{"lock":false,"pos":{"x":-21.105,"y":1.0062,"z":35.175},"rot":{"x":0,"y":180,"z":0}},"6a4c70":{"lock":false,"pos":{"x":-22.1294,"y":1.2735,"z":-22.3986},"rot":{"x":0,"y":180.0008,"z":180}},"c9abd6":{"lock":false,"pos":{"x":-23.6401,"y":1.0736,"z":-16.7396},"rot":{"x":0,"y":179.9855,"z":180}},"d7503a":{"lock":false,"pos":{"x":-12.75,"y":0.9736,"z":22.25},"rot":{"x":0,"y":179.9743,"z":180}}},"ml4":{"00f91e":{"lock":true,"pos":{"x":-13.7113,"y":0.96,"z":-17.7527},"rot":{"x":0,"y":179.9851,"z":0}},"08b295":{"lock":true,"pos":{"x":-24.1417,"y":1.06,"z":-12.2398},"rot":{"x":0,"y":179.9845,"z":0}},"45b260":{"lock":false,"pos":{"x":-21.105,"y":1.0062,"z":35.175},"rot":{"x":0,"y":180,"z":0}},"65e798":{"lock":false,"pos":{"x":-22.1294,"y":1.1531,"z":-22.3986},"rot":{"x":0,"y":180.0172,"z":0}},"c9abd6":{"lock":false,"pos":{"x":-23.6401,"y":1.0736,"z":-16.7396},"rot":{"x":0,"y":179.9855,"z":180}},"d7503a":{"lock":false,"pos":{"x":-12.75,"y":0.9736,"z":22.25},"rot":{"x":0,"y":179.9743,"z":180}}},"ml5":{"00f91e":{"lock":true,"pos":{"x":13.7582,"y":0.96,"z":-17.7621},"rot":{"x":0,"y":180.016,"z":0}},"08b295":{"lock":true,"pos":{"x":3.3307,"y":1.06,"z":-12.2435},"rot":{"x":0.0001,"y":180.0184,"z":0}},"45b260":{"lock":false,"pos":{"x":-21.105,"y":1.0062,"z":35.175},"rot":{"x":0,"y":180,"z":0}},"6a4c70":{"lock":false,"pos":{"x":5.3375,"y":1.2735,"z":-22.4034},"rot":{"x":0,"y":180.0009,"z":180}},"c9abd6":{"lock":false,"pos":{"x":3.8299,"y":1.0736,"z":-16.7436},"rot":{"x":0,"y":180.0172,"z":180}},"d7503a":{"lock":false,"pos":{"x":-12.75,"y":0.9736,"z":22.25},"rot":{"x":0,"y":179.9743,"z":180}}},"ml6":{"00f91e":{"lock":true,"pos":{"x":13.7582,"y":0.96,"z":-17.7621},"rot":{"x":0,"y":180.016,"z":0}},"08b295":{"lock":true,"pos":{"x":3.3307,"y":1.06,"z":-12.2435},"rot":{"x":0.0001,"y":180.0184,"z":0}},"45b260":{"lock":false,"pos":{"x":-21.105,"y":1.0062,"z":35.175},"rot":{"x":0,"y":180,"z":0}},"65e798":{"lock":false,"pos":{"x":5.3375,"y":1.1531,"z":-22.4034},"rot":{"x":0,"y":179.9747,"z":0}},"c9abd6":{"lock":false,"pos":{"x":3.8299,"y":1.0736,"z":-16.7436},"rot":{"x":0,"y":180.0172,"z":180}},"d7503a":{"lock":false,"pos":{"x":-12.75,"y":0.9736,"z":22.25},"rot":{"x":0,"y":179.9743,"z":180}}},"ml7":{"00f91e":{"lock":true,"pos":{"x":41.1934,"y":0.961,"z":-17.0888},"rot":{"x":-0.0003,"y":180.0121,"z":-0.0032}},"08b295":{"lock":true,"pos":{"x":30.7684,"y":1.0604,"z":-11.5657},"rot":{"x":-0.0003,"y":179.9951,"z":-0.0033}},"45b260":{"lock":false,"pos":{"x":-21.105,"y":1.0062,"z":35.175},"rot":{"x":0,"y":180,"z":0}},"6a4c70":{"lock":false,"pos":{"x":32.7731,"y":1.2741,"z":-21.7308},"rot":{"x":-0.0003,"y":180.0009,"z":179.9967}},"c9abd6":{"lock":false,"pos":{"x":31.2656,"y":1.074,"z":-16.066},"rot":{"x":-0.0004,"y":180.0224,"z":179.9967}},"d7503a":{"lock":false,"pos":{"x":-12.75,"y":0.9736,"z":22.25},"rot":{"x":0,"y":179.9743,"z":180}}},"ml8":{"00f91e":{"lock":true,"pos":{"x":41.1934,"y":0.961,"z":-17.0888},"rot":{"x":-0.0003,"y":180.0121,"z":-0.0032}},"08b295":{"lock":true,"pos":{"x":30.7684,"y":1.0604,"z":-11.5657},"rot":{"x":-0.0003,"y":179.9951,"z":-0.0033}},"45b260":{"lock":false,"pos":{"x":-21.105,"y":1.0062,"z":35.175},"rot":{"x":0,"y":180,"z":0}},"65e798":{"lock":false,"pos":{"x":32.7731,"y":1.1537,"z":-21.7308},"rot":{"x":-0.0003,"y":179.9747,"z":-0.0033}},"c9abd6":{"lock":false,"pos":{"x":31.2656,"y":1.074,"z":-16.066},"rot":{"x":-0.0004,"y":180.0224,"z":179.9967}},"d7503a":{"lock":false,"pos":{"x":-12.75,"y":0.9736,"z":22.25},"rot":{"x":0,"y":179.9743,"z":180}}}}
