{
  "Object": {
    "GUID": "28c6b9",
    "Name": "Custom_Tile",
    "Transform": {
      "posX": 63.2499924,
      "posY": 0.495001554,
      "posZ": 23.7500038,
      "rotX": 0.000002384813,
      "rotY": 179.999924,
      "rotZ": 1.43118285e-7,
      "scaleX": 1.11,
      "scaleY": 1,
      "scaleZ": 1.11
    },
    "Nickname": "Quicksilver",
    "Description": "",
    "GMNotes": "",
    "ColorDiffuse": {
      "r": 0.249970764,
      "g": 0.249970764,
      "b": 0.249970764
    },
    "LayoutGroupSortIndex": 0,
    "Value": 0,
    "Locked": true,
    "Grid": true,
    "Snap": true,
    "IgnoreFoW": false,
    "MeasureMovement": false,
    "DragSelectable": true,
    "Autoraise": true,
    "Sticky": true,
    "Tooltip": true,
    "GridProjection": false,
    "HideWhenFaceDown": false,
    "Hands": false,
    "CustomImage": {
      "ImageURL": "http://cloud-3.steamusercontent.com/ugc/1759188247845742509/7FF3ADF7F8499AAB61FE09FE82ABB688481275DE/",
      "ImageSecondaryURL": "http://cloud-3.steamusercontent.com/ugc/1683744853795306585/08D73433C8AB0861DD4A3B9A5E66E7849F26898F/",
      "ImageScalar": 1,
      "WidthScale": 0,
      "CustomTile": {
        "Type": 3,
        "Thickness": 0.197297364,
        "Stackable": false,
        "Stretch": true
      }
    },
    "LuaScript": "",
    "LuaScriptState": "#include ./Quicksilver.28c6b9.state.json",
    "XmlUI": ""
  },
  "StatesPaths": {}
}
